{"expires":1733180104672,"value":{"code":200,"headers":{"etag":"W/\"nEqCbl003B\"","last-modified":"Mon, 25 Nov 2024 22:55:04 GMT","cache-control":"s-maxage=604800, stale-while-revalidate"},"body":{"prefix":"heroicons","icons":{"pencil":{"body":"<path fill=\"none\" stroke=\"currentColor\" stroke-linecap=\"round\" stroke-linejoin=\"round\" stroke-width=\"1.5\" d=\"m16.862 4.487l1.687-1.688a1.875 1.875 0 1 1 2.652 2.652L6.832 19.82a4.5 4.5 0 0 1-1.897 1.13l-2.685.8l.8-2.685a4.5 4.5 0 0 1 1.13-1.897zm0 0L19.5 7.125\"/>"},"phone":{"body":"<path fill=\"none\" stroke=\"currentColor\" stroke-linecap=\"round\" stroke-linejoin=\"round\" stroke-width=\"1.5\" d=\"M2.25 6.75c0 8.284 6.716 15 15 15h2.25a2.25 2.25 0 0 0 2.25-2.25v-1.372c0-.516-.351-.966-.852-1.091l-4.423-1.106c-.44-.11-.902.055-1.173.417l-.97 1.293c-.282.376-.769.542-1.21.38a12.04 12.04 0 0 1-7.143-7.143c-.162-.441.004-.928.38-1.21l1.293-.97c.363-.271.527-.734.417-1.173L6.963 3.102a1.125 1.125 0 0 0-1.091-.852H4.5A2.25 2.25 0 0 0 2.25 4.5z\"/>"},"plus":{"body":"<path fill=\"none\" stroke=\"currentColor\" stroke-linecap=\"round\" stroke-linejoin=\"round\" stroke-width=\"1.5\" d=\"M12 4.5v15m7.5-7.5h-15\"/>"},"user":{"body":"<path fill=\"none\" stroke=\"currentColor\" stroke-linecap=\"round\" stroke-linejoin=\"round\" stroke-width=\"1.5\" d=\"M15.75 6a3.75 3.75 0 1 1-7.5 0a3.75 3.75 0 0 1 7.5 0M4.501 20.118a7.5 7.5 0 0 1 14.998 0A17.9 17.9 0 0 1 12 21.75c-2.676 0-5.216-.584-7.499-1.632\"/>"}},"lastModified":1721921294,"width":24,"height":24}},"mtime":1732575304698,"integrity":"7lfF5RINRs"}